pyswx/__init__.py
pyswx/__main__.py
pyswx/api/__init__.py
pyswx/api/base_interface.py
pyswx/api/sldworks/__init__.py
pyswx/api/sldworks/interfaces/__init__.py
pyswx/api/sldworks/interfaces/i_advanced_save_as_options.py
pyswx/api/sldworks/interfaces/i_assembly_doc.py
pyswx/api/sldworks/interfaces/i_component_2.py
pyswx/api/sldworks/interfaces/i_configuration.py
pyswx/api/sldworks/interfaces/i_configuration_manager.py
pyswx/api/sldworks/interfaces/i_custom_property_manager.py
pyswx/api/sldworks/interfaces/i_dim_xpert_manager.py
pyswx/api/sldworks/interfaces/i_display_dimension.py
pyswx/api/sldworks/interfaces/i_document_specification.py
pyswx/api/sldworks/interfaces/i_drawing_doc.py
pyswx/api/sldworks/interfaces/i_enum_bodies_2.py
pyswx/api/sldworks/interfaces/i_explode_step.py
pyswx/api/sldworks/interfaces/i_export_pdf_data.py
pyswx/api/sldworks/interfaces/i_frame.py
pyswx/api/sldworks/interfaces/i_math_transform.py
pyswx/api/sldworks/interfaces/i_model_doc_2.py
pyswx/api/sldworks/interfaces/i_model_doc_extension.py
pyswx/api/sldworks/interfaces/i_model_window.py
pyswx/api/sldworks/interfaces/i_part_doc.py
pyswx/api/sldworks/interfaces/i_sldworks.py
pyswx/api/sldworks/interfaces/i_status_bar_pane.py
pyswx/api/sldworks/interfaces/i_view.py
pyswx/api/swconst/__init__.py
pyswx/api/swconst/enumerations/__init__.py
pyswx/api/swconst/enumerations/sw_3d_experience_cfg_type_e.py
pyswx/api/swconst/enumerations/sw_activate_doc_error_e.py
pyswx/api/swconst/enumerations/sw_add_to_recent_document_list_e.py
pyswx/api/swconst/enumerations/sw_app_notify_e.py
pyswx/api/swconst/enumerations/sw_application_type_e.py
pyswx/api/swconst/enumerations/sw_assembly_load_components_e.py
pyswx/api/swconst/enumerations/sw_body_type_e.py
pyswx/api/swconst/enumerations/sw_bom_configuration_anchor_type_e.py
pyswx/api/swconst/enumerations/sw_cad_family_cfg_options_e.py
pyswx/api/swconst/enumerations/sw_child_component_in_bom_option_e.py
pyswx/api/swconst/enumerations/sw_close_reopen_error_e.py
pyswx-0.6.0.dist-info/licenses/LICENSE
pyswx-0.6.0.dist-info/METADATA
pyswx-0.6.0.dist-info/WHEEL
pyswx-0.6.0.dist-info/RECORD
