Metadata-Version: 2.4
Name: pyswx
Version: 0.6.0
Summary: A python wrapper for the SolidWorks API.
License: MIT
License-File: LICENSE
Keywords: solidworks,sldworks
Author: Philip Delorenzo
Author-email: git@deloarts.com
Maintainer: Philip Delorenzo
Maintainer-email: git@deloarts.com
Requires-Python: >=3.12
Classifier: Environment :: Win32 (MS Windows)
Classifier: Intended Audience :: Manufacturing
Classifier: License :: OSI Approved :: MIT License
Classifier: Operating System :: Microsoft :: Windows :: Windows 11
Classifier: Programming Language :: Python :: 3
Classifier: Programming Language :: Python :: 3.12
Classifier: Programming Language :: Python :: 3.13
Classifier: Programming Language :: Python :: 3.14
Requires-Dist: pywin32 (>=310,<311)
